{
    "title": "Typographie",
    "status": "ready",
    "default": "default",
    "context": {},
    "variants": [
        {
            "name": "default",
            "label": "Titres",
            "context": {
                "h1": "Ceci est un titre de niveau 1",
                "h2": "Ceci est un titre de niveau 2",
                "h3": "Ceci est un titre de niveau 3",
                "h4": "Ceci est un titre de niveau 4",
                "h5": "Ceci est un titre de niveau 5",
                "h6": "Ceci est un titre de niveau 6"
            }
        },
        {
            "name": "h-with-sub",
            "label": "Titres alternatifs",
            "context": {
                "h1": "Ceci est un titre de niveau 1",
                "h2": "Ceci est un titre de niveau 2",
                "h3": "Ceci est un titre de niveau 3",
                "h4": "Ceci est un titre de niveau 4",
                "h5": "Ceci est un titre de niveau 5",
                "h6": "Ceci est un titre de niveau 6"
            }
        },
        {
            "name": "p",
            "label": "Paragraphe",
            "context": {
                "text": "Lorem ipsum dolor sit amet, consectetur adipiscing elit. Cras rutrum id lacus quis volutpat. Suspendisse dictum eros vitae nunc mattis molestie. Sed placerat dolor id enim dignissim, a finibus nunc maximus. Vivamus sed nisl nec justo consequat malesuada ac vitae sem. Vivamus consequat vitae orci auctor gravida."
            }
        },
        {
            "name": "a",
            "label": "Lien",
            "context": {
                "text": "Ceci est un hyperlien"
            }
        }
    ]
}